.gitignore
.travis.yml
README.rst
bootstrap.py
buildout-cache.cfg
buildout.cfg
setup.cfg
setup.py
travis-4.1.cfg
travis-4.2.cfg
travis-4.3.cfg
collective/__init__.py
collective.facets.egg-info/PKG-INFO
collective.facets.egg-info/SOURCES.txt
collective.facets.egg-info/dependency_links.txt
collective.facets.egg-info/entry_points.txt
collective.facets.egg-info/namespace_packages.txt
collective.facets.egg-info/not-zip-safe
collective.facets.egg-info/requires.txt
collective.facets.egg-info/top_level.txt
collective/facets/__init__.py
collective/facets/browser.py
collective/facets/configure.zcml
collective/facets/interfaces.py
collective/facets/schema.py
collective/facets/testing.py
collective/facets/userlist.py
collective/facets/utils.py
collective/facets/validation.py
collective/facets/vocabularies.py
collective/facets/profiles/default/browserlayer.xml
collective/facets/profiles/default/controlpanel.xml
collective/facets/profiles/default/metadata.xml
collective/facets/profiles/default/registry.xml
collective/facets/tests/__init__.py
collective/facets/tests/test_facets.py
conf/test-4.2.x.cfg
docs/HISTORY.txt
docs/INSTALL.txt
docs/LICENSE.GPL
docs/LICENSE.txt
parts/omelette/collective/facets/__init__.py
parts/omelette/collective/facets/browser.py
parts/omelette/collective/facets/configure.zcml
parts/omelette/collective/facets/interfaces.py
parts/omelette/collective/facets/schema.py
parts/omelette/collective/facets/testing.py
parts/omelette/collective/facets/userlist.py
parts/omelette/collective/facets/utils.py
parts/omelette/collective/facets/validation.py
parts/omelette/collective/facets/vocabularies.py
parts/omelette/collective/facets/profiles/default/browserlayer.xml
parts/omelette/collective/facets/profiles/default/controlpanel.xml
parts/omelette/collective/facets/profiles/default/metadata.xml
parts/omelette/collective/facets/profiles/default/registry.xml
parts/omelette/collective/facets/tests/__init__.py
parts/omelette/collective/facets/tests/test_facets.py