Metadata-Version: 1.1
Name: collective.facets
Version: 1.2
Summary: Let's users add new facets to all content
Home-page: https://github.com/collective/collective.facets
Author: Dylan Jay
Author-email: software@pretaweb.com
License: GPL
Platform: UNKNOWN
Classifier: Framework :: Plone
Classifier: Programming Language :: Python
